[
  {
    "id": "performance-patterns-import-on-interaction-1",
    "title": "What is the main goal of the Import On Interaction pattern?",
    "content": "Import On Interaction delays the loading of non-critical resources until the user interacts with the UI element that requires them, improving page load performance.",
    "type": "mcq",
    "category": "Performance Patterns",
    "topic": "Lazy Loading",
    "difficulty": "beginner",
    "learningCardId": "system-design",
    "isActive": true,
    "createdAt": "2025-10-10T00:00:00Z",
    "updatedAt": "2025-10-10T00:00:00Z",
    "createdBy": "admin",
    "updatedBy": "admin",
    "tags": ["performance-patterns", "lazy-loading", "beginner"],
    "explanation": "The Import On Interaction pattern improves load performance by deferring loading of non-critical JavaScript until a user interacts with a relevant element.",
    "points": 10,
    "options": [
      {
        "0": "T",
        "1": "o",
        "2": " ",
        "3": "l",
        "4": "o",
        "5": "a",
        "6": "d",
        "7": " ",
        "8": "a",
        "9": "l",
        "10": "l",
        "11": " ",
        "12": "s",
        "13": "c",
        "14": "r",
        "15": "i",
        "16": "p",
        "17": "t",
        "18": "s",
        "19": " ",
        "20": "e",
        "21": "a",
        "22": "g",
        "23": "e",
        "24": "r",
        "25": "l",
        "26": "y",
        "27": " ",
        "28": "o",
        "29": "n",
        "30": " ",
        "31": "p",
        "32": "a",
        "33": "g",
        "34": "e",
        "35": " ",
        "36": "l",
        "37": "o",
        "38": "a",
        "39": "d",
        "explanation": ""
      },
      {
        "0": "T",
        "1": "o",
        "2": " ",
        "3": "l",
        "4": "a",
        "5": "z",
        "6": "y",
        "7": "-",
        "8": "l",
        "9": "o",
        "10": "a",
        "11": "d",
        "12": " ",
        "13": "n",
        "14": "o",
        "15": "n",
        "16": "-",
        "17": "c",
        "18": "r",
        "19": "i",
        "20": "t",
        "21": "i",
        "22": "c",
        "23": "a",
        "24": "l",
        "25": " ",
        "26": "r",
        "27": "e",
        "28": "s",
        "29": "o",
        "30": "u",
        "31": "r",
        "32": "c",
        "33": "e",
        "34": "s",
        "35": " ",
        "36": "w",
        "37": "h",
        "38": "e",
        "39": "n",
        "40": " ",
        "41": "n",
        "42": "e",
        "43": "e",
        "44": "d",
        "45": "e",
        "46": "d",
        "explanation": ""
      },
      {
        "0": "T",
        "1": "o",
        "2": " ",
        "3": "c",
        "4": "o",
        "5": "m",
        "6": "p",
        "7": "i",
        "8": "l",
        "9": "e",
        "10": " ",
        "11": "c",
        "12": "o",
        "13": "d",
        "14": "e",
        "15": " ",
        "16": "d",
        "17": "u",
        "18": "r",
        "19": "i",
        "20": "n",
        "21": "g",
        "22": " ",
        "23": "b",
        "24": "u",
        "25": "i",
        "26": "l",
        "27": "d",
        "28": " ",
        "29": "t",
        "30": "i",
        "31": "m",
        "32": "e",
        "explanation": ""
      },
      {
        "0": "T",
        "1": "o",
        "2": " ",
        "3": "i",
        "4": "m",
        "5": "p",
        "6": "r",
        "7": "o",
        "8": "v",
        "9": "e",
        "10": " ",
        "11": "S",
        "12": "E",
        "13": "O",
        "14": " ",
        "15": "r",
        "16": "a",
        "17": "n",
        "18": "k",
        "19": "i",
        "20": "n",
        "21": "g",
        "explanation": ""
      }
    ],
    "sampleAnswers": ["To lazy-load non-critical resources when needed"],
    "hints": [],
    "metadata": {}
  },
  {
    "id": "performance-patterns-import-on-interaction-2",
    "title": "Which user actions typically trigger Import On Interaction?",
    "content": "The pattern can be triggered when a user clicks, scrolls into view, or when the browser is idle.",
    "type": "mcq",
    "category": "Performance Patterns",
    "topic": "User Interaction Events",
    "difficulty": "intermediate",
    "learningCardId": "system-design",
    "isActive": true,
    "createdAt": "2025-10-10T00:00:00Z",
    "updatedAt": "2025-10-10T00:00:00Z",
    "createdBy": "admin",
    "updatedBy": "admin",
    "tags": ["performance-patterns", "user-interaction-events", null],
    "explanation": "The pattern optimizes performance by waiting for direct user interactions or idle time before loading heavy resources.",
    "points": 10,
    "options": [
      {
        "0": "O",
        "1": "n",
        "2": "l",
        "3": "y",
        "4": " ",
        "5": "w",
        "6": "h",
        "7": "e",
        "8": "n",
        "9": " ",
        "10": "a",
        "11": " ",
        "12": "u",
        "13": "s",
        "14": "e",
        "15": "r",
        "16": " ",
        "17": "r",
        "18": "e",
        "19": "f",
        "20": "r",
        "21": "e",
        "22": "s",
        "23": "h",
        "24": "e",
        "25": "s",
        "26": " ",
        "27": "t",
        "28": "h",
        "29": "e",
        "30": " ",
        "31": "p",
        "32": "a",
        "33": "g",
        "34": "e",
        "explanation": ""
      },
      {
        "0": "O",
        "1": "n",
        "2": " ",
        "3": "u",
        "4": "s",
        "5": "e",
        "6": "r",
        "7": " ",
        "8": "c",
        "9": "l",
        "10": "i",
        "11": "c",
        "12": "k",
        "13": ",",
        "14": " ",
        "15": "s",
        "16": "c",
        "17": "r",
        "18": "o",
        "19": "l",
        "20": "l",
        "21": ",",
        "22": " ",
        "23": "o",
        "24": "r",
        "25": " ",
        "26": "i",
        "27": "d",
        "28": "l",
        "29": "e",
        "30": " ",
        "31": "t",
        "32": "i",
        "33": "m",
        "34": "e",
        "explanation": ""
      },
      {
        "0": "W",
        "1": "h",
        "2": "e",
        "3": "n",
        "4": " ",
        "5": "d",
        "6": "a",
        "7": "t",
        "8": "a",
        "9": " ",
        "10": "f",
        "11": "e",
        "12": "t",
        "13": "c",
        "14": "h",
        "15": "i",
        "16": "n",
        "17": "g",
        "18": " ",
        "19": "c",
        "20": "o",
        "21": "m",
        "22": "p",
        "23": "l",
        "24": "e",
        "25": "t",
        "26": "e",
        "27": "s",
        "explanation": ""
      },
      {
        "0": "D",
        "1": "u",
        "2": "r",
        "3": "i",
        "4": "n",
        "5": "g",
        "6": " ",
        "7": "s",
        "8": "e",
        "9": "r",
        "10": "v",
        "11": "e",
        "12": "r",
        "13": "-",
        "14": "s",
        "15": "i",
        "16": "d",
        "17": "e",
        "18": " ",
        "19": "r",
        "20": "e",
        "21": "n",
        "22": "d",
        "23": "e",
        "24": "r",
        "25": "i",
        "26": "n",
        "27": "g",
        "explanation": ""
      }
    ],
    "sampleAnswers": ["On user click, scroll, or idle time"],
    "hints": [],
    "metadata": {}
  },
  {
    "id": "performance-patterns-import-on-interaction-3",
    "title": "What is a facade in Import On Interaction?",
    "content": "A facade is a lightweight placeholder or preview that mimics a heavy component until the user interacts with it.",
    "type": "mcq",
    "category": "Performance Patterns",
    "topic": "Facades and Placeholders",
    "difficulty": "intermediate",
    "learningCardId": "system-design",
    "isActive": true,
    "createdAt": "2025-10-10T00:00:00Z",
    "updatedAt": "2025-10-10T00:00:00Z",
    "createdBy": "admin",
    "updatedBy": "admin",
    "tags": ["performance-patterns", "facades-and-placeholders", null],
    "explanation": "A facade prevents heavy resources from loading immediately by displaying a placeholder (like a thumbnail or fake button) until the user interacts.",
    "points": 10,
    "options": [
      {
        "0": "A",
        "1": " ",
        "2": "p",
        "3": "l",
        "4": "a",
        "5": "c",
        "6": "e",
        "7": "h",
        "8": "o",
        "9": "l",
        "10": "d",
        "11": "e",
        "12": "r",
        "13": " ",
        "14": "e",
        "15": "l",
        "16": "e",
        "17": "m",
        "18": "e",
        "19": "n",
        "20": "t",
        "21": " ",
        "22": "s",
        "23": "h",
        "24": "o",
        "25": "w",
        "26": "n",
        "27": " ",
        "28": "b",
        "29": "e",
        "30": "f",
        "31": "o",
        "32": "r",
        "33": "e",
        "34": " ",
        "35": "r",
        "36": "e",
        "37": "a",
        "38": "l",
        "39": " ",
        "40": "c",
        "41": "o",
        "42": "n",
        "43": "t",
        "44": "e",
        "45": "n",
        "46": "t",
        "47": " ",
        "48": "l",
        "49": "o",
        "50": "a",
        "51": "d",
        "52": "s",
        "explanation": ""
      },
      {
        "0": "A",
        "1": " ",
        "2": "t",
        "3": "y",
        "4": "p",
        "5": "e",
        "6": " ",
        "7": "o",
        "8": "f",
        "9": " ",
        "10": "R",
        "11": "e",
        "12": "a",
        "13": "c",
        "14": "t",
        "15": " ",
        "16": "c",
        "17": "o",
        "18": "m",
        "19": "p",
        "20": "o",
        "21": "n",
        "22": "e",
        "23": "n",
        "24": "t",
        "explanation": ""
      },
      {
        "0": "A",
        "1": " ",
        "2": "t",
        "3": "h",
        "4": "i",
        "5": "r",
        "6": "d",
        "7": "-",
        "8": "p",
        "9": "a",
        "10": "r",
        "11": "t",
        "12": "y",
        "13": " ",
        "14": "A",
        "15": "P",
        "16": "I",
        "17": " ",
        "18": "o",
        "19": "p",
        "20": "t",
        "21": "i",
        "22": "m",
        "23": "i",
        "24": "z",
        "25": "a",
        "26": "t",
        "27": "i",
        "28": "o",
        "29": "n",
        "30": " ",
        "31": "t",
        "32": "o",
        "33": "o",
        "34": "l",
        "explanation": ""
      },
      {
        "0": "A",
        "1": " ",
        "2": "p",
        "3": "e",
        "4": "r",
        "5": "f",
        "6": "o",
        "7": "r",
        "8": "m",
        "9": "a",
        "10": "n",
        "11": "c",
        "12": "e",
        "13": " ",
        "14": "m",
        "15": "o",
        "16": "n",
        "17": "i",
        "18": "t",
        "19": "o",
        "20": "r",
        "21": "i",
        "22": "n",
        "23": "g",
        "24": " ",
        "25": "t",
        "26": "e",
        "27": "c",
        "28": "h",
        "29": "n",
        "30": "i",
        "31": "q",
        "32": "u",
        "33": "e",
        "explanation": ""
      }
    ],
    "sampleAnswers": ["A placeholder element shown before real content loads"],
    "hints": [],
    "metadata": {}
  },
  {
    "id": "performance-patterns-import-on-interaction-4",
    "title": "What problem does Import On Interaction solve with third-party scripts?",
    "content": "Third-party scripts can block rendering or hydration. Import On Interaction delays their load until user interaction.",
    "type": "mcq",
    "category": "Performance Patterns",
    "topic": "Third-Party Script Optimization",
    "difficulty": "intermediate",
    "learningCardId": "system-design",
    "isActive": true,
    "createdAt": "2025-10-10T00:00:00Z",
    "updatedAt": "2025-10-10T00:00:00Z",
    "createdBy": "admin",
    "updatedBy": "admin",
    "tags": ["performance-patterns", "third-party-script-optimization", null],
    "explanation": "By loading third-party scripts only when needed, the main thread remains available for critical tasks like rendering and user input.",
    "points": 10,
    "options": [
      {
        "0": "I",
        "1": "t",
        "2": " ",
        "3": "b",
        "4": "l",
        "5": "o",
        "6": "c",
        "7": "k",
        "8": "s",
        "9": " ",
        "10": "t",
        "11": "h",
        "12": "i",
        "13": "r",
        "14": "d",
        "15": "-",
        "16": "p",
        "17": "a",
        "18": "r",
        "19": "t",
        "20": "y",
        "21": " ",
        "22": "s",
        "23": "c",
        "24": "r",
        "25": "i",
        "26": "p",
        "27": "t",
        "28": "s",
        "29": " ",
        "30": "c",
        "31": "o",
        "32": "m",
        "33": "p",
        "34": "l",
        "35": "e",
        "36": "t",
        "37": "e",
        "38": "l",
        "39": "y",
        "explanation": ""
      },
      {
        "0": "I",
        "1": "t",
        "2": " ",
        "3": "e",
        "4": "n",
        "5": "s",
        "6": "u",
        "7": "r",
        "8": "e",
        "9": "s",
        "10": " ",
        "11": "t",
        "12": "h",
        "13": "i",
        "14": "r",
        "15": "d",
        "16": "-",
        "17": "p",
        "18": "a",
        "19": "r",
        "20": "t",
        "21": "y",
        "22": " ",
        "23": "s",
        "24": "c",
        "25": "r",
        "26": "i",
        "27": "p",
        "28": "t",
        "29": "s",
        "30": " ",
        "31": "l",
        "32": "o",
        "33": "a",
        "34": "d",
        "35": " ",
        "36": "b",
        "37": "e",
        "38": "f",
        "39": "o",
        "40": "r",
        "41": "e",
        "42": " ",
        "43": "f",
        "44": "i",
        "45": "r",
        "46": "s",
        "47": "t",
        "48": " ",
        "49": "p",
        "50": "a",
        "51": "i",
        "52": "n",
        "53": "t",
        "explanation": ""
      },
      {
        "0": "I",
        "1": "t",
        "2": " ",
        "3": "d",
        "4": "e",
        "5": "f",
        "6": "e",
        "7": "r",
        "8": "s",
        "9": " ",
        "10": "n",
        "11": "o",
        "12": "n",
        "13": "-",
        "14": "c",
        "15": "r",
        "16": "i",
        "17": "t",
        "18": "i",
        "19": "c",
        "20": "a",
        "21": "l",
        "22": " ",
        "23": "t",
        "24": "h",
        "25": "i",
        "26": "r",
        "27": "d",
        "28": "-",
        "29": "p",
        "30": "a",
        "31": "r",
        "32": "t",
        "33": "y",
        "34": " ",
        "35": "s",
        "36": "c",
        "37": "r",
        "38": "i",
        "39": "p",
        "40": "t",
        "41": "s",
        "42": " ",
        "43": "u",
        "44": "n",
        "45": "t",
        "46": "i",
        "47": "l",
        "48": " ",
        "49": "n",
        "50": "e",
        "51": "e",
        "52": "d",
        "53": "e",
        "54": "d",
        "explanation": ""
      },
      {
        "0": "I",
        "1": "t",
        "2": " ",
        "3": "p",
        "4": "r",
        "5": "e",
        "6": "l",
        "7": "o",
        "8": "a",
        "9": "d",
        "10": "s",
        "11": " ",
        "12": "a",
        "13": "l",
        "14": "l",
        "15": " ",
        "16": "e",
        "17": "x",
        "18": "t",
        "19": "e",
        "20": "r",
        "21": "n",
        "22": "a",
        "23": "l",
        "24": " ",
        "25": "s",
        "26": "c",
        "27": "r",
        "28": "i",
        "29": "p",
        "30": "t",
        "31": "s",
        "explanation": ""
      }
    ],
    "sampleAnswers": [
      "It defers non-critical third-party scripts until needed"
    ],
    "hints": [],
    "metadata": {}
  },
  {
    "id": "performance-patterns-import-on-interaction-5",
    "title": "Which metrics can Import On Interaction improve?",
    "content": "By reducing blocking resources, it improves First Input Delay (FID), Total Blocking Time (TBT), and Time to Interactive (TTI).",
    "type": "mcq",
    "category": "Performance Patterns",
    "topic": "Web Vitals",
    "difficulty": "intermediate",
    "learningCardId": "system-design",
    "isActive": true,
    "createdAt": "2025-10-10T00:00:00Z",
    "updatedAt": "2025-10-10T00:00:00Z",
    "createdBy": "admin",
    "updatedBy": "admin",
    "tags": ["performance-patterns", "web-vitals", null],
    "explanation": "Deferring heavy scripts helps the browser respond to user input faster, improving FID, TBT, and TTI metrics.",
    "points": 10,
    "options": [
      {
        "0": "L",
        "1": "a",
        "2": "r",
        "3": "g",
        "4": "e",
        "5": "s",
        "6": "t",
        "7": " ",
        "8": "C",
        "9": "o",
        "10": "n",
        "11": "t",
        "12": "e",
        "13": "n",
        "14": "t",
        "15": "f",
        "16": "u",
        "17": "l",
        "18": " ",
        "19": "P",
        "20": "a",
        "21": "i",
        "22": "n",
        "23": "t",
        "24": " ",
        "25": "(",
        "26": "L",
        "27": "C",
        "28": "P",
        "29": ")",
        "30": " ",
        "31": "a",
        "32": "n",
        "33": "d",
        "34": " ",
        "35": "C",
        "36": "u",
        "37": "m",
        "38": "u",
        "39": "l",
        "40": "a",
        "41": "t",
        "42": "i",
        "43": "v",
        "44": "e",
        "45": " ",
        "46": "L",
        "47": "a",
        "48": "y",
        "49": "o",
        "50": "u",
        "51": "t",
        "52": " ",
        "53": "S",
        "54": "h",
        "55": "i",
        "56": "f",
        "57": "t",
        "58": " ",
        "59": "(",
        "60": "C",
        "61": "L",
        "62": "S",
        "63": ")",
        "explanation": ""
      },
      {
        "0": "F",
        "1": "i",
        "2": "r",
        "3": "s",
        "4": "t",
        "5": " ",
        "6": "I",
        "7": "n",
        "8": "p",
        "9": "u",
        "10": "t",
        "11": " ",
        "12": "D",
        "13": "e",
        "14": "l",
        "15": "a",
        "16": "y",
        "17": " ",
        "18": "(",
        "19": "F",
        "20": "I",
        "21": "D",
        "22": ")",
        "23": ",",
        "24": " ",
        "25": "T",
        "26": "o",
        "27": "t",
        "28": "a",
        "29": "l",
        "30": " ",
        "31": "B",
        "32": "l",
        "33": "o",
        "34": "c",
        "35": "k",
        "36": "i",
        "37": "n",
        "38": "g",
        "39": " ",
        "40": "T",
        "41": "i",
        "42": "m",
        "43": "e",
        "44": " ",
        "45": "(",
        "46": "T",
        "47": "B",
        "48": "T",
        "49": ")",
        "50": ",",
        "51": " ",
        "52": "T",
        "53": "i",
        "54": "m",
        "55": "e",
        "56": " ",
        "57": "t",
        "58": "o",
        "59": " ",
        "60": "I",
        "61": "n",
        "62": "t",
        "63": "e",
        "64": "r",
        "65": "a",
        "66": "c",
        "67": "t",
        "68": "i",
        "69": "v",
        "70": "e",
        "71": " ",
        "72": "(",
        "73": "T",
        "74": "T",
        "75": "I",
        "76": ")",
        "explanation": ""
      },
      {
        "0": "B",
        "1": "o",
        "2": "u",
        "3": "n",
        "4": "c",
        "5": "e",
        "6": " ",
        "7": "r",
        "8": "a",
        "9": "t",
        "10": "e",
        "11": " ",
        "12": "a",
        "13": "n",
        "14": "d",
        "15": " ",
        "16": "S",
        "17": "E",
        "18": "O",
        "19": " ",
        "20": "r",
        "21": "a",
        "22": "n",
        "23": "k",
        "24": "i",
        "25": "n",
        "26": "g",
        "explanation": ""
      },
      {
        "0": "S",
        "1": "e",
        "2": "r",
        "3": "v",
        "4": "e",
        "5": "r",
        "6": " ",
        "7": "r",
        "8": "e",
        "9": "s",
        "10": "p",
        "11": "o",
        "12": "n",
        "13": "s",
        "14": "e",
        "15": " ",
        "16": "t",
        "17": "i",
        "18": "m",
        "19": "e",
        "20": " ",
        "21": "a",
        "22": "n",
        "23": "d",
        "24": " ",
        "25": "b",
        "26": "a",
        "27": "n",
        "28": "d",
        "29": "w",
        "30": "i",
        "31": "d",
        "32": "t",
        "33": "h",
        "explanation": ""
      }
    ],
    "sampleAnswers": [
      "First Input Delay (FID), Total Blocking Time (TBT), Time to Interactive (TTI)"
    ],
    "hints": [],
    "metadata": {}
  },
  {
    "id": "performance-patterns-import-on-interaction-6",
    "title": "Which JavaScript feature enables dynamic Import On Interaction?",
    "content": "The dynamic `import()` function allows modules to be loaded only when needed.",
    "type": "mcq",
    "category": "Performance Patterns",
    "topic": "Dynamic Imports",
    "difficulty": "beginner",
    "learningCardId": "system-design",
    "isActive": true,
    "createdAt": "2025-10-10T00:00:00Z",
    "updatedAt": "2025-10-10T00:00:00Z",
    "createdBy": "admin",
    "updatedBy": "admin",
    "tags": ["performance-patterns", "dynamic-imports", "beginner"],
    "explanation": "Dynamic `import()` returns a promise and can load modules lazily, which is ideal for import-on-interaction use cases.",
    "points": 10,
    "options": [
      {
        "0": "r",
        "1": "e",
        "2": "q",
        "3": "u",
        "4": "i",
        "5": "r",
        "6": "e",
        "7": "(",
        "8": ")",
        "explanation": ""
      },
      {
        "0": "i",
        "1": "m",
        "2": "p",
        "3": "o",
        "4": "r",
        "5": "t",
        "6": " ",
        "7": "*",
        "8": " ",
        "9": "f",
        "10": "r",
        "11": "o",
        "12": "m",
        "13": " ",
        "14": "'",
        "15": "m",
        "16": "o",
        "17": "d",
        "18": "u",
        "19": "l",
        "20": "e",
        "21": "'",
        "explanation": ""
      },
      {
        "0": "d",
        "1": "y",
        "2": "n",
        "3": "a",
        "4": "m",
        "5": "i",
        "6": "c",
        "7": " ",
        "8": "i",
        "9": "m",
        "10": "p",
        "11": "o",
        "12": "r",
        "13": "t",
        "14": "(",
        "15": ")",
        "explanation": ""
      },
      {
        "0": "a",
        "1": "s",
        "2": "y",
        "3": "n",
        "4": "c",
        "5": " ",
        "6": "a",
        "7": "w",
        "8": "a",
        "9": "i",
        "10": "t",
        "explanation": ""
      }
    ],
    "sampleAnswers": ["dynamic import()"],
    "hints": [],
    "metadata": {}
  },
  {
    "id": "performance-patterns-import-on-interaction-7",
    "title": "How does React support Import On Interaction?",
    "content": "React supports lazy-loading components using React.lazy and Suspense, or by dynamically importing a component on user interaction.",
    "type": "mcq",
    "category": "Performance Patterns",
    "topic": "React Lazy Loading",
    "difficulty": "intermediate",
    "learningCardId": "system-design",
    "isActive": true,
    "createdAt": "2025-10-10T00:00:00Z",
    "updatedAt": "2025-10-10T00:00:00Z",
    "createdBy": "admin",
    "updatedBy": "admin",
    "tags": ["performance-patterns", "react-lazy-loading", null],
    "explanation": "React’s `lazy()` and `Suspense` make it easy to defer loading non-critical components until interaction occurs.",
    "points": 10,
    "options": [
      {
        "0": "B",
        "1": "y",
        "2": " ",
        "3": "c",
        "4": "o",
        "5": "m",
        "6": "p",
        "7": "i",
        "8": "l",
        "9": "i",
        "10": "n",
        "11": "g",
        "12": " ",
        "13": "c",
        "14": "o",
        "15": "m",
        "16": "p",
        "17": "o",
        "18": "n",
        "19": "e",
        "20": "n",
        "21": "t",
        "22": "s",
        "23": " ",
        "24": "o",
        "25": "n",
        "26": " ",
        "27": "t",
        "28": "h",
        "29": "e",
        "30": " ",
        "31": "s",
        "32": "e",
        "33": "r",
        "34": "v",
        "35": "e",
        "36": "r",
        "explanation": ""
      },
      {
        "0": "U",
        "1": "s",
        "2": "i",
        "3": "n",
        "4": "g",
        "5": " ",
        "6": "R",
        "7": "e",
        "8": "a",
        "9": "c",
        "10": "t",
        "11": ".",
        "12": "l",
        "13": "a",
        "14": "z",
        "15": "y",
        "16": " ",
        "17": "a",
        "18": "n",
        "19": "d",
        "20": " ",
        "21": "S",
        "22": "u",
        "23": "s",
        "24": "p",
        "25": "e",
        "26": "n",
        "27": "s",
        "28": "e",
        "29": " ",
        "30": "o",
        "31": "r",
        "32": " ",
        "33": "d",
        "34": "y",
        "35": "n",
        "36": "a",
        "37": "m",
        "38": "i",
        "39": "c",
        "40": " ",
        "41": "i",
        "42": "m",
        "43": "p",
        "44": "o",
        "45": "r",
        "46": "t",
        "47": " ",
        "48": "o",
        "49": "n",
        "50": " ",
        "51": "c",
        "52": "l",
        "53": "i",
        "54": "c",
        "55": "k",
        "explanation": ""
      },
      {
        "0": "B",
        "1": "y",
        "2": " ",
        "3": "u",
        "4": "s",
        "5": "i",
        "6": "n",
        "7": "g",
        "8": " ",
        "9": "R",
        "10": "e",
        "11": "a",
        "12": "c",
        "13": "t",
        "14": ".",
        "15": "u",
        "16": "s",
        "17": "e",
        "18": "M",
        "19": "e",
        "20": "m",
        "21": "o",
        "22": " ",
        "23": "f",
        "24": "o",
        "25": "r",
        "26": " ",
        "27": "c",
        "28": "a",
        "29": "c",
        "30": "h",
        "31": "i",
        "32": "n",
        "33": "g",
        "explanation": ""
      },
      {
        "0": "T",
        "1": "h",
        "2": "r",
        "3": "o",
        "4": "u",
        "5": "g",
        "6": "h",
        "7": " ",
        "8": "h",
        "9": "y",
        "10": "d",
        "11": "r",
        "12": "a",
        "13": "t",
        "14": "i",
        "15": "o",
        "16": "n",
        "17": " ",
        "18": "d",
        "19": "e",
        "20": "l",
        "21": "a",
        "22": "y",
        "23": " ",
        "24": "A",
        "25": "P",
        "26": "I",
        "27": "s",
        "explanation": ""
      }
    ],
    "sampleAnswers": [
      "Using React.lazy and Suspense or dynamic import on click"
    ],
    "hints": [],
    "metadata": {}
  },
  {
    "id": "performance-patterns-import-on-interaction-8",
    "title": "What trade-off can occur with Import On Interaction?",
    "content": "Users may experience a delay after clicking while the script loads if the resource is large or network is slow.",
    "type": "mcq",
    "category": "Performance Patterns",
    "topic": "Performance Trade-offs",
    "difficulty": "intermediate",
    "learningCardId": "system-design",
    "isActive": true,
    "createdAt": "2025-10-10T00:00:00Z",
    "updatedAt": "2025-10-10T00:00:00Z",
    "createdBy": "admin",
    "updatedBy": "admin",
    "tags": ["performance-patterns", "performance-trade-offs", null],
    "explanation": "While the page loads faster initially, there might be a small delay when the resource is fetched on demand.",
    "points": 10,
    "options": [
      {
        "0": "R",
        "1": "e",
        "2": "d",
        "3": "u",
        "4": "c",
        "5": "e",
        "6": "d",
        "7": " ",
        "8": "m",
        "9": "e",
        "10": "m",
        "11": "o",
        "12": "r",
        "13": "y",
        "14": " ",
        "15": "u",
        "16": "s",
        "17": "a",
        "18": "g",
        "19": "e",
        "explanation": ""
      },
      {
        "0": "I",
        "1": "n",
        "2": "s",
        "3": "t",
        "4": "a",
        "5": "n",
        "6": "t",
        "7": "a",
        "8": "n",
        "9": "e",
        "10": "o",
        "11": "u",
        "12": "s",
        "13": " ",
        "14": "i",
        "15": "n",
        "16": "t",
        "17": "e",
        "18": "r",
        "19": "a",
        "20": "c",
        "21": "t",
        "22": "i",
        "23": "v",
        "24": "i",
        "25": "t",
        "26": "y",
        "27": " ",
        "28": "a",
        "29": "l",
        "30": "w",
        "31": "a",
        "32": "y",
        "33": "s",
        "explanation": ""
      },
      {
        "0": "P",
        "1": "o",
        "2": "s",
        "3": "s",
        "4": "i",
        "5": "b",
        "6": "l",
        "7": "e",
        "8": " ",
        "9": "d",
        "10": "e",
        "11": "l",
        "12": "a",
        "13": "y",
        "14": " ",
        "15": "a",
        "16": "f",
        "17": "t",
        "18": "e",
        "19": "r",
        "20": " ",
        "21": "u",
        "22": "s",
        "23": "e",
        "24": "r",
        "25": " ",
        "26": "i",
        "27": "n",
        "28": "t",
        "29": "e",
        "30": "r",
        "31": "a",
        "32": "c",
        "33": "t",
        "34": "i",
        "35": "o",
        "36": "n",
        "explanation": ""
      },
      {
        "0": "I",
        "1": "m",
        "2": "p",
        "3": "r",
        "4": "o",
        "5": "v",
        "6": "e",
        "7": "d",
        "8": " ",
        "9": "S",
        "10": "E",
        "11": "O",
        "12": " ",
        "13": "p",
        "14": "e",
        "15": "r",
        "16": "f",
        "17": "o",
        "18": "r",
        "19": "m",
        "20": "a",
        "21": "n",
        "22": "c",
        "23": "e",
        "explanation": ""
      }
    ],
    "sampleAnswers": ["Possible delay after user interaction"],
    "hints": [],
    "metadata": {}
  },
  {
    "id": "performance-patterns-import-on-interaction-9",
    "title": "What is an example of Import On Interaction in Google Docs?",
    "content": "Google Docs loads the 500KB share feature script only when the user clicks the Share button.",
    "type": "mcq",
    "category": "Performance Patterns",
    "topic": "Real World Example",
    "difficulty": "beginner",
    "learningCardId": "system-design",
    "isActive": true,
    "createdAt": "2025-10-10T00:00:00Z",
    "updatedAt": "2025-10-10T00:00:00Z",
    "createdBy": "admin",
    "updatedBy": "admin",
    "tags": ["performance-patterns", "real-world-example", "beginner"],
    "explanation": "Google Docs defers loading large non-critical scripts until the user actually interacts with the Share feature.",
    "points": 10,
    "options": [
      {
        "0": "I",
        "1": "t",
        "2": " ",
        "3": "p",
        "4": "r",
        "5": "e",
        "6": "l",
        "7": "o",
        "8": "a",
        "9": "d",
        "10": "s",
        "11": " ",
        "12": "a",
        "13": "l",
        "14": "l",
        "15": " ",
        "16": "s",
        "17": "c",
        "18": "r",
        "19": "i",
        "20": "p",
        "21": "t",
        "22": "s",
        "23": " ",
        "24": "o",
        "25": "n",
        "26": " ",
        "27": "s",
        "28": "t",
        "29": "a",
        "30": "r",
        "31": "t",
        "32": "u",
        "33": "p",
        "explanation": ""
      },
      {
        "0": "I",
        "1": "t",
        "2": " ",
        "3": "l",
        "4": "o",
        "5": "a",
        "6": "d",
        "7": "s",
        "8": " ",
        "9": "t",
        "10": "h",
        "11": "e",
        "12": " ",
        "13": "s",
        "14": "h",
        "15": "a",
        "16": "r",
        "17": "e",
        "18": " ",
        "19": "f",
        "20": "e",
        "21": "a",
        "22": "t",
        "23": "u",
        "24": "r",
        "25": "e",
        "26": " ",
        "27": "d",
        "28": "y",
        "29": "n",
        "30": "a",
        "31": "m",
        "32": "i",
        "33": "c",
        "34": "a",
        "35": "l",
        "36": "l",
        "37": "y",
        "38": " ",
        "39": "o",
        "40": "n",
        "41": " ",
        "42": "c",
        "43": "l",
        "44": "i",
        "45": "c",
        "46": "k",
        "explanation": ""
      },
      {
        "0": "I",
        "1": "t",
        "2": " ",
        "3": "b",
        "4": "l",
        "5": "o",
        "6": "c",
        "7": "k",
        "8": "s",
        "9": " ",
        "10": "t",
        "11": "h",
        "12": "e",
        "13": " ",
        "14": "m",
        "15": "a",
        "16": "i",
        "17": "n",
        "18": " ",
        "19": "t",
        "20": "h",
        "21": "r",
        "22": "e",
        "23": "a",
        "24": "d",
        "25": " ",
        "26": "f",
        "27": "o",
        "28": "r",
        "29": " ",
        "30": "p",
        "31": "e",
        "32": "r",
        "33": "f",
        "34": "o",
        "35": "r",
        "36": "m",
        "37": "a",
        "38": "n",
        "39": "c",
        "40": "e",
        "explanation": ""
      },
      {
        "0": "I",
        "1": "t",
        "2": " ",
        "3": "d",
        "4": "i",
        "5": "s",
        "6": "a",
        "7": "b",
        "8": "l",
        "9": "e",
        "10": "s",
        "11": " ",
        "12": "u",
        "13": "s",
        "14": "e",
        "15": "r",
        "16": " ",
        "17": "i",
        "18": "n",
        "19": "t",
        "20": "e",
        "21": "r",
        "22": "a",
        "23": "c",
        "24": "t",
        "25": "i",
        "26": "o",
        "27": "n",
        "28": "s",
        "29": " ",
        "30": "d",
        "31": "u",
        "32": "r",
        "33": "i",
        "34": "n",
        "35": "g",
        "36": " ",
        "37": "l",
        "38": "o",
        "39": "a",
        "40": "d",
        "explanation": ""
      }
    ],
    "sampleAnswers": ["It loads the share feature dynamically on click"],
    "hints": [],
    "metadata": {}
  },
  {
    "id": "performance-patterns-import-on-interaction-10",
    "title": "What is a common use case for Import On Interaction with third-party widgets?",
    "content": "Loading chat widgets, video players, or authentication SDKs only after user interaction to save initial load time.",
    "type": "mcq",
    "category": "Performance Patterns",
    "topic": "Third-Party Optimization",
    "difficulty": "intermediate",
    "learningCardId": "system-design",
    "isActive": true,
    "createdAt": "2025-10-10T00:00:00Z",
    "updatedAt": "2025-10-10T00:00:00Z",
    "createdBy": "admin",
    "updatedBy": "admin",
    "tags": ["performance-patterns", "third-party-optimization", null],
    "explanation": "Deferring third-party widget code until interaction avoids blocking critical rendering and reduces main-thread congestion.",
    "points": 10,
    "options": [
      {
        "0": "P",
        "1": "r",
        "2": "e",
        "3": "l",
        "4": "o",
        "5": "a",
        "6": "d",
        "7": "i",
        "8": "n",
        "9": "g",
        "10": " ",
        "11": "a",
        "12": "l",
        "13": "l",
        "14": " ",
        "15": "e",
        "16": "x",
        "17": "t",
        "18": "e",
        "19": "r",
        "20": "n",
        "21": "a",
        "22": "l",
        "23": " ",
        "24": "S",
        "25": "D",
        "26": "K",
        "27": "s",
        "explanation": ""
      },
      {
        "0": "L",
        "1": "a",
        "2": "z",
        "3": "y",
        "4": "-",
        "5": "l",
        "6": "o",
        "7": "a",
        "8": "d",
        "9": "i",
        "10": "n",
        "11": "g",
        "12": " ",
        "13": "n",
        "14": "o",
        "15": "n",
        "16": "-",
        "17": "c",
        "18": "r",
        "19": "i",
        "20": "t",
        "21": "i",
        "22": "c",
        "23": "a",
        "24": "l",
        "25": " ",
        "26": "t",
        "27": "h",
        "28": "i",
        "29": "r",
        "30": "d",
        "31": "-",
        "32": "p",
        "33": "a",
        "34": "r",
        "35": "t",
        "36": "y",
        "37": " ",
        "38": "w",
        "39": "i",
        "40": "d",
        "41": "g",
        "42": "e",
        "43": "t",
        "44": "s",
        "explanation": ""
      },
      {
        "0": "L",
        "1": "o",
        "2": "a",
        "3": "d",
        "4": "i",
        "5": "n",
        "6": "g",
        "7": " ",
        "8": "a",
        "9": "l",
        "10": "l",
        "11": " ",
        "12": "w",
        "13": "i",
        "14": "d",
        "15": "g",
        "16": "e",
        "17": "t",
        "18": "s",
        "19": " ",
        "20": "s",
        "21": "y",
        "22": "n",
        "23": "c",
        "24": "h",
        "25": "r",
        "26": "o",
        "27": "n",
        "28": "o",
        "29": "u",
        "30": "s",
        "31": "l",
        "32": "y",
        "explanation": ""
      },
      {
        "0": "D",
        "1": "i",
        "2": "s",
        "3": "a",
        "4": "b",
        "5": "l",
        "6": "i",
        "7": "n",
        "8": "g",
        "9": " ",
        "10": "w",
        "11": "i",
        "12": "d",
        "13": "g",
        "14": "e",
        "15": "t",
        "16": "s",
        "17": " ",
        "18": "f",
        "19": "o",
        "20": "r",
        "21": " ",
        "22": "p",
        "23": "e",
        "24": "r",
        "25": "f",
        "26": "o",
        "27": "r",
        "28": "m",
        "29": "a",
        "30": "n",
        "31": "c",
        "32": "e",
        "explanation": ""
      }
    ],
    "sampleAnswers": ["Lazy-loading non-critical third-party widgets"],
    "hints": [],
    "metadata": {}
  }
]
